CHANGELOG.md
xleap/__init__.py
xleap/_client/__init__.py
xleap/_client/api/__init__.py
xleap/_client/api/v1_api.py
xleap/_client/api_client.py
xleap/_client/api_response.py
xleap/_client/configuration.py
xleap/_client/docs/APIKey.md
xleap/_client/docs/APIKeyUpdate.md
xleap/_client/docs/ChartData.md
xleap/_client/docs/DataPoint.md
xleap/_client/docs/DataPointCreate.md
xleap/_client/docs/DataPointResult.md
xleap/_client/docs/ExchangeTokenRequest.md
xleap/_client/docs/ExchangeTokenRequestUser.md
xleap/_client/docs/ListAPIKeys200Response.md
xleap/_client/docs/ListDataPoints200Response.md
xleap/_client/docs/ListMLModels200Response.md
xleap/_client/docs/ListMetricsDatas200Response.md
xleap/_client/docs/ListOrgLists200Response.md
xleap/_client/docs/ListProjects200Response.md
xleap/_client/docs/ListPrompts200Response.md
xleap/_client/docs/ListRuns200Response.md
xleap/_client/docs/MLModel.md
xleap/_client/docs/Metrics.md
xleap/_client/docs/OrgDetail.md
xleap/_client/docs/OrgDetailMembersInner.md
xleap/_client/docs/OrgList.md
xleap/_client/docs/OrgMember.md
xleap/_client/docs/Project.md
xleap/_client/docs/ProjectConfig.md
xleap/_client/docs/ProjectCreate.md
xleap/_client/docs/ProjectCreateConfig.md
xleap/_client/docs/ProjectDetail.md
xleap/_client/docs/Prompt.md
xleap/_client/docs/Run.md
xleap/_client/docs/RunCreate.md
xleap/_client/docs/TokenObtain.md
xleap/_client/docs/TokenResponse.md
xleap/_client/docs/UserPreference.md
xleap/_client/docs/V1Api.md
xleap/_client/exceptions.py
xleap/_client/models/__init__.py
xleap/_client/models/api_key.py
xleap/_client/models/api_key_update.py
xleap/_client/models/chart_data.py
xleap/_client/models/data_point.py
xleap/_client/models/data_point_create.py
xleap/_client/models/data_point_result.py
xleap/_client/models/exchange_token_request.py
xleap/_client/models/exchange_token_request_user.py
xleap/_client/models/list_api_keys200_response.py
xleap/_client/models/list_data_points200_response.py
xleap-0.1.6.dist-info/METADATA
xleap-0.1.6.dist-info/WHEEL
xleap-0.1.6.dist-info/RECORD
