Metadata-Version: 2.1
Name: xleap
Version: 0.1.6
Summary: xleap's python sdk
Home-page: https://xleaplabs.com
Author: Pritam Soni
Author-email: 23050213+pritamsoni-hsr@users.noreply.github.com
Requires-Python: >=3.11,<4.0
Classifier: Programming Language :: Python :: 3
Classifier: Programming Language :: Python :: 3.11
Classifier: Programming Language :: Python :: 3.12
Provides-Extra: all
Requires-Dist: attrs (>=21.3.0)
Requires-Dist: langchain (>=0.1.7,<0.2.0)
Requires-Dist: numpy (==1.23.5)
Requires-Dist: openai (>=1.9.0,<2.0.0)
Requires-Dist: pandas (>=1.5.3,<2.0.0)
Requires-Dist: python-dateutil (>=2.8.0,<3.0.0)
Requires-Dist: rich (>=13.7.0,<14.0.0)
Requires-Dist: rouge-score (>=0.1.2,<0.2.0)
Requires-Dist: textstat (>=0.7.3,<0.8.0)
Requires-Dist: typer (>=0.9.0,<0.10.0)
Project-URL: Documentation, http://docs.xleaplabs.com
Project-URL: Repository, https://github.com/xleap-ai/xleap
